Metadata-Version: 2.1
Name: pepsepy
Version: 0.0.1
Summary: python package for PEPSE project
Home-page: https://gitlab.com/vlle-cenaero/pepsepy
Author: Van Long LE
Author-email: vanlong.le@cenaero.be
License: MIT
Platform: UNKNOWN
Classifier: License :: OSI Approved :: MIT License
Classifier: Programming Language :: Python
Classifier: Programming Language :: Python :: 3
Classifier: Programming Language :: Python :: 3.6
Classifier: Programming Language :: Python :: Implementation :: CPython
Classifier: Programming Language :: Python :: Implementation :: PyPy
Requires-Python: >=3.6.0
